llamadeck/__init__.py
llamadeck/config.py
llamadeck/main.py
llama_deck-1.0.0.post1.dist-info/LICENSE
llama_deck-1.0.0.post1.dist-info/METADATA
llama_deck-1.0.0.post1.dist-info/WHEEL
llama_deck-1.0.0.post1.dist-info/entry_points.txt
llama_deck-1.0.0.post1.dist-info/top_level.txt
llama_deck-1.0.0.post1.dist-info/RECORD
